{
    "GRPCPort": 8020,

    "HTTPPort": 8021,
    "HTTPReadTimeout": 10,
    "HTTPWriteTimeout": 10,

    "WebsocketPort": 8022,
    "WebsocketTimeout": 10,

    "KafkaBrokerAddr": ["kafka-0.kafka-headless:9092", "kafka-1.kafka-headless:9092", "kafka-3.kafka-headless:9092"],
    "KafkaSASLUsername": "kafkacli",
    "KafkaSASLPassword": "kafkaclipws",
    "KafkaMsgTopic": "chat",
    "MysqlAddr": "mysql-0.mysql:3306",
    "MysqlUsername": "root",
    "MysqlPassword": "root",
    "RedisAddr": "redis-0.redis:6379",
    "RedisUsername": "root",
    "RedisPassword": "root",
    "MongoAddr": "",
    "MongoUsername": "root",
    "MongoPassword": "root"
}